FlightRadar24/__init__.py
FlightRadar24/api.py
FlightRadar24/core.py
FlightRadar24/errors.py
FlightRadar24/request.py
FlightRadar24/entities/__init__.py
FlightRadar24/entities/airport.py
FlightRadar24/entities/entity.py
FlightRadar24/entities/flight.py
flightradarapi-1.3.32.dist-info/METADATA
flightradarapi-1.3.32.dist-info/WHEEL
flightradarapi-1.3.32.dist-info/licenses/LICENSE
flightradarapi-1.3.32.dist-info/RECORD
