Metadata-Version: 2.3
Name: FlightRadarAPI
Version: 1.3.32
Summary: SDK for FlightRadar24
Project-URL: Homepage, https://github.com/JeanExtreme002/FlightRadarAPI
Project-URL: Source Code, https://github.com/JeanExtreme002/FlightRadarAPI
Project-URL: Documentation, https://jeanextreme002.github.io/FlightRadarAPI/
Project-URL: Bug Reports, https://github.com/JeanExtreme002/FlightRadarAPI/issues
Author-email: Jean Loui Bernard Silva de Jesus <jeanextreme002@gmail.com>
License-Expression: MIT
License-File: LICENSE
Keywords: aircraft,airlines,airports,api,aviation,flightradar24,flights,radar
Classifier: License :: OSI Approved :: MIT License
Classifier: Programming Language :: Python :: 3 :: Only
Classifier: Programming Language :: Python :: 3.7
Classifier: Programming Language :: Python :: 3.8
Classifier: Programming Language :: Python :: 3.9
Classifier: Programming Language :: Python :: 3.10
Classifier: Programming Language :: Python :: 3.11
Requires-Python: >=3.7
Requires-Dist: brotli
Requires-Dist: requests
Provides-Extra: tests
Requires-Dist: pytest; extra == 'tests'
